{
  "El Rubín (JAÉN) - agosto 2025 -grf_agosto": {
    "title": "El Rubín (JAÉN) - agosto 2025 -grf",
    "month": "agosto",
    "plazas_disponibles": 2,
    "timestamp": "2025-08-01T21:40:12.881473"
  },
  "Curso anual estudios n- La Cañada (VALENCIA)- agosto 2025 - alf_agosto": {
    "title": "Curso anual estudios n- La Cañada (VALENCIA)- agosto 2025 - alf",
    "month": "agosto",
    "plazas_disponibles": 2,
    "timestamp": "2025-08-01T21:40:12.881482"
  },
  "Can Viladoms (BARCELONA )- agosto 2025- bf_agosto": {
    "title": "Can Viladoms (BARCELONA )- agosto 2025- bf",
    "month": "agosto",
    "plazas_disponibles": 2,
    "timestamp": "2025-08-01T21:40:12.881485"
  },
  "Coniston Hall (MANCHESTER) - agosto 2025 - nf_agosto": {
    "title": "Coniston Hall (MANCHESTER) - agosto 2025 - nf",
    "month": "agosto",
    "plazas_disponibles": 3,
    "timestamp": "2025-08-01T21:40:12.881487"
  },
  "Can Nadal (GIRONA )- agosto 2025- bf_agosto": {
    "title": "Can Nadal (GIRONA )- agosto 2025- bf",
    "month": "agosto",
    "plazas_disponibles": 3,
    "timestamp": "2025-08-01T21:40:12.881489"
  },
  "Can Soteras (BARCELONA)- agosto 2025 - bf_agosto": {
    "title": "Can Soteras (BARCELONA)- agosto 2025 - bf",
    "month": "agosto",
    "plazas_disponibles": 1,
    "timestamp": "2025-08-01T21:40:12.881492"
  },
  "Las Acacias (VIGO) - agosto 2025_agosto": {
    "title": "Las Acacias (VIGO) - agosto 2025",
    "month": "agosto",
    "plazas_disponibles": 2,
    "timestamp": "2025-08-01T21:40:12.881495"
  },
  "Piñeiral - (ARZÚA. A CORUÑA) - agosto 2025_agosto": {
    "title": "Piñeiral - (ARZÚA. A CORUÑA) - agosto 2025",
    "month": "agosto",
    "plazas_disponibles": 5,
    "timestamp": "2025-08-01T21:40:12.881499"
  },
  "Hotel Cinco castaños (CANDELARIO-SALAMANCA) - agosto 2025_agosto": {
    "title": "Hotel Cinco castaños (CANDELARIO-SALAMANCA) - agosto 2025",
    "month": "agosto",
    "plazas_disponibles": 2,
    "timestamp": "2025-08-01T21:40:12.881502"
  },
  "Valdearroyo pb (MADRID) - agosto 2025 - mof_agosto": {
    "title": "Valdearroyo pb (MADRID) - agosto 2025 - mof",
    "month": "agosto",
    "plazas_disponibles": 4,
    "timestamp": "2025-08-01T21:40:12.881504"
  },
  "Alcor (MADRID) - agosto 2025 - mof_agosto": {
    "title": "Alcor (MADRID) - agosto 2025 - mof",
    "month": "agosto",
    "plazas_disponibles": 6,
    "timestamp": "2025-08-01T21:40:12.881506"
  },
  "Los Álamos (SEVILLA) - agosto 2025 - sf_agosto": {
    "title": "Los Álamos (SEVILLA) - agosto 2025 - sf",
    "month": "agosto",
    "plazas_disponibles": 1,
    "timestamp": "2025-08-01T21:40:12.881509"
  },
  "Los Enebros (MADRID) - agosto 2025 - mof_agosto": {
    "title": "Los Enebros (MADRID) - agosto 2025 - mof",
    "month": "agosto",
    "plazas_disponibles": 1,
    "timestamp": "2025-08-01T21:40:12.881511"
  },
  "Abiria (A CORUÑA) - agosto 2025 - nf_agosto": {
    "title": "Abiria (A CORUÑA) - agosto 2025 - nf",
    "month": "agosto",
    "plazas_disponibles": 1,
    "timestamp": "2025-08-01T21:40:12.881513"
  },
  "Campolargo (ZARAGOZA)- agosto 2025 - alf_agosto": {
    "title": "Campolargo (ZARAGOZA)- agosto 2025 - alf",
    "month": "agosto",
    "plazas_disponibles": 6,
    "timestamp": "2025-08-01T21:40:12.881515"
  },
  "Alsajara (GRANADA) - agosto 2025- grf_agosto": {
    "title": "Alsajara (GRANADA) - agosto 2025- grf",
    "month": "agosto",
    "plazas_disponibles": 2,
    "timestamp": "2025-08-01T21:40:12.881517"
  },
  "Hotel Orri (Vall d'Aran) - agosto 2025- bf_agosto": {
    "title": "Hotel Orri (Vall d'Aran) - agosto 2025- bf",
    "month": "agosto",
    "plazas_disponibles": 1,
    "timestamp": "2025-08-01T21:40:12.881519"
  },
  "Valparaiso - (SEVILLA) - agosto 2025 -sf_agosto": {
    "title": "Valparaiso - (SEVILLA) - agosto 2025 -sf",
    "month": "agosto",
    "plazas_disponibles": 1,
    "timestamp": "2025-08-01T21:40:12.881522"
  }
}