{
  "Valparaiso (SEVILLA) - julio/agosto 2025 - sf_julio": {
    "title": "Valparaiso (SEVILLA) - julio/agosto 2025 - sf",
    "month": "julio",
    "plazas_disponibles": 4,
    "timestamp": "2025-07-19T04:50:50.694531"
  },
  "Can Viladoms (BARCELONA )- agosto 2025- bf_agosto": {
    "title": "Can Viladoms (BARCELONA )- agosto 2025- bf",
    "month": "agosto",
    "plazas_disponibles": 3,
    "timestamp": "2025-07-19T04:50:50.694541"
  },
  "Coniston Hall (MANCHESTER) - agosto 2025 - nf_agosto": {
    "title": "Coniston Hall (MANCHESTER) - agosto 2025 - nf",
    "month": "agosto",
    "plazas_disponibles": 4,
    "timestamp": "2025-07-19T04:50:50.694544"
  },
  "Rua Nueva (Santiago de Compostela) - agosto 2025- pf_agosto": {
    "title": "Rua Nueva (Santiago de Compostela) - agosto 2025- pf",
    "month": "agosto",
    "plazas_disponibles": 1,
    "timestamp": "2025-07-19T04:50:50.694546"
  },
  "Can Nadal (GIRONA )- agosto 2025- bf_agosto": {
    "title": "Can Nadal (GIRONA )- agosto 2025- bf",
    "month": "agosto",
    "plazas_disponibles": 2,
    "timestamp": "2025-07-19T04:50:50.694549"
  },
  "Las Acacias (VIGO) - agosto 2025_agosto": {
    "title": "Las Acacias (VIGO) - agosto 2025",
    "month": "agosto",
    "plazas_disponibles": 2,
    "timestamp": "2025-07-19T04:50:50.694551"
  },
  "Piñeiral - (ARZÚA. A CORUÑA) - agosto 2025_agosto": {
    "title": "Piñeiral - (ARZÚA. A CORUÑA) - agosto 2025",
    "month": "agosto",
    "plazas_disponibles": 5,
    "timestamp": "2025-07-19T04:50:50.694554"
  },
  "Hotel Cinco castaños (CANDELARIO-SALAMANCA) - agosto 2025_agosto": {
    "title": "Hotel Cinco castaños (CANDELARIO-SALAMANCA) - agosto 2025",
    "month": "agosto",
    "plazas_disponibles": 3,
    "timestamp": "2025-07-19T04:50:50.694558"
  },
  "Valdearroyo pb (MADRID) - agosto 2025 - mof_agosto": {
    "title": "Valdearroyo pb (MADRID) - agosto 2025 - mof",
    "month": "agosto",
    "plazas_disponibles": 1,
    "timestamp": "2025-07-19T04:50:50.694561"
  },
  "Alcor (MADRID) - agosto 2025 - mof_agosto": {
    "title": "Alcor (MADRID) - agosto 2025 - mof",
    "month": "agosto",
    "plazas_disponibles": 6,
    "timestamp": "2025-07-19T04:50:50.694563"
  },
  "Hotel SNÖ (FORMIGAL)- agosto 2025 - bf_agosto": {
    "title": "Hotel SNÖ (FORMIGAL)- agosto 2025 - bf",
    "month": "agosto",
    "plazas_disponibles": 1,
    "timestamp": "2025-07-19T04:50:50.694565"
  },
  "Los Enebros (MADRID) - agosto 2025 - mof_agosto": {
    "title": "Los Enebros (MADRID) - agosto 2025 - mof",
    "month": "agosto",
    "plazas_disponibles": 4,
    "timestamp": "2025-07-19T04:50:50.694568"
  },
  "Campolargo (ZARAGOZA)- agosto 2025 - alf_agosto": {
    "title": "Campolargo (ZARAGOZA)- agosto 2025 - alf",
    "month": "agosto",
    "plazas_disponibles": 4,
    "timestamp": "2025-07-19T04:50:50.694570"
  },
  "Hotel Orri (Vall d'Aran) - agosto 2025- bf_agosto": {
    "title": "Hotel Orri (Vall d'Aran) - agosto 2025- bf",
    "month": "agosto",
    "plazas_disponibles": 1,
    "timestamp": "2025-07-19T04:50:50.694572"
  },
  "Láriz (VIZCAYA) - agosto/septiembre 2025 - pf_agosto": {
    "title": "Láriz (VIZCAYA) - agosto/septiembre 2025 - pf",
    "month": "agosto",
    "plazas_disponibles": 1,
    "timestamp": "2025-07-19T04:50:50.694574"
  }
}