{
  "Curso anual estudios n- La Lloma pb (VALENCIA)- agosto 2025 - alf_agosto": {
    "title": "Curso anual estudios n- La Lloma pb (VALENCIA)- agosto 2025 - alf",
    "month": "agosto",
    "plazas_disponibles": 1,
    "timestamp": "2025-07-26T15:42:18.413523"
  },
  "Can Viladoms (BARCELONA )- agosto 2025- bf_agosto": {
    "title": "Can Viladoms (BARCELONA )- agosto 2025- bf",
    "month": "agosto",
    "plazas_disponibles": 3,
    "timestamp": "2025-07-26T15:42:18.413531"
  },
  "Coniston Hall (MANCHESTER) - agosto 2025 - nf_agosto": {
    "title": "Coniston Hall (MANCHESTER) - agosto 2025 - nf",
    "month": "agosto",
    "plazas_disponibles": 3,
    "timestamp": "2025-07-26T15:42:18.413534"
  },
  "Can Nadal (GIRONA )- agosto 2025- bf_agosto": {
    "title": "Can Nadal (GIRONA )- agosto 2025- bf",
    "month": "agosto",
    "plazas_disponibles": 2,
    "timestamp": "2025-07-26T15:42:18.413536"
  },
  "Hotel Edelweiss (CERLER)- agosto 2025 - bf_agosto": {
    "title": "Hotel Edelweiss (CERLER)- agosto 2025 - bf",
    "month": "agosto",
    "plazas_disponibles": 1,
    "timestamp": "2025-07-26T15:42:18.413539"
  },
  "Can Soteras (BARCELONA)- agosto 2025 - bf_agosto": {
    "title": "Can Soteras (BARCELONA)- agosto 2025 - bf",
    "month": "agosto",
    "plazas_disponibles": 3,
    "timestamp": "2025-07-26T15:42:18.413542"
  },
  "Las Acacias (VIGO) - agosto 2025_agosto": {
    "title": "Las Acacias (VIGO) - agosto 2025",
    "month": "agosto",
    "plazas_disponibles": 2,
    "timestamp": "2025-07-26T15:42:18.413544"
  },
  "Piñeiral - (ARZÚA. A CORUÑA) - agosto 2025_agosto": {
    "title": "Piñeiral - (ARZÚA. A CORUÑA) - agosto 2025",
    "month": "agosto",
    "plazas_disponibles": 5,
    "timestamp": "2025-07-26T15:42:18.413548"
  },
  "Hotel Cinco castaños (CANDELARIO-SALAMANCA) - agosto 2025_agosto": {
    "title": "Hotel Cinco castaños (CANDELARIO-SALAMANCA) - agosto 2025",
    "month": "agosto",
    "plazas_disponibles": 3,
    "timestamp": "2025-07-26T15:42:18.413550"
  },
  "Valdearroyo pb (MADRID) - agosto 2025 - mof_agosto": {
    "title": "Valdearroyo pb (MADRID) - agosto 2025 - mof",
    "month": "agosto",
    "plazas_disponibles": 1,
    "timestamp": "2025-07-26T15:42:18.413551"
  },
  "Alcor (MADRID) - agosto 2025 - mof_agosto": {
    "title": "Alcor (MADRID) - agosto 2025 - mof",
    "month": "agosto",
    "plazas_disponibles": 6,
    "timestamp": "2025-07-26T15:42:18.413553"
  },
  "Hotel SNÖ (FORMIGAL)- agosto 2025 - bf_agosto": {
    "title": "Hotel SNÖ (FORMIGAL)- agosto 2025 - bf",
    "month": "agosto",
    "plazas_disponibles": 1,
    "timestamp": "2025-07-26T15:42:18.413554"
  },
  "Los Enebros (MADRID) - agosto 2025 - mof_agosto": {
    "title": "Los Enebros (MADRID) - agosto 2025 - mof",
    "month": "agosto",
    "plazas_disponibles": 3,
    "timestamp": "2025-07-26T15:42:18.413555"
  },
  "Abiria (A CORUÑA) - agosto 2025 - nf_agosto": {
    "title": "Abiria (A CORUÑA) - agosto 2025 - nf",
    "month": "agosto",
    "plazas_disponibles": 1,
    "timestamp": "2025-07-26T15:42:18.413557"
  },
  "Campolargo (ZARAGOZA)- agosto 2025 - alf_agosto": {
    "title": "Campolargo (ZARAGOZA)- agosto 2025 - alf",
    "month": "agosto",
    "plazas_disponibles": 5,
    "timestamp": "2025-07-26T15:42:18.413558"
  },
  "Alsajara (GRANADA) - agosto 2025- grf_agosto": {
    "title": "Alsajara (GRANADA) - agosto 2025- grf",
    "month": "agosto",
    "plazas_disponibles": 1,
    "timestamp": "2025-07-26T15:42:18.413559"
  },
  "Valparaiso - (SEVILLA) - agosto 2025 -sf_agosto": {
    "title": "Valparaiso - (SEVILLA) - agosto 2025 -sf",
    "month": "agosto",
    "plazas_disponibles": 2,
    "timestamp": "2025-07-26T15:42:18.413560"
  }
}